{"nodes": [{"id": "examples_list_widget_main_go", "label": "main.go", "file_type": "code", "source_file": "examples/list_widget/main.go", "source_location": "L1"}, {"id": "list_widget_game", "label": "Game", "file_type": "code", "source_file": "examples/list_widget/main.go", "source_location": "L40"}, {"id": "main_main", "label": "main()", "file_type": "code", "source_file": "examples/list_widget/main.go", "source_location": "L44"}, {"id": "list_widget_game_update", "label": ".Update()", "file_type": "code", "source_file": "examples/list_widget/main.go", "source_location": "L117"}, {"id": "list_widget_game_draw", "label": ".Draw()", "file_type": "code", "source_file": "examples/list_widget/main.go", "source_location": "L125"}, {"id": "list_widget_game_layout", "label": ".Layout()", "file_type": "code", "source_file": "examples/list_widget/main.go", "source_location": "L132"}, {"id": "main_loadfont", "label": "loadFont()", "file_type": "code", "source_file": "examples/list_widget/main.go", "source_location": "L136"}, {"id": "main_createbuttonimage", "label": "createButtonImage()", "file_type": "code", "source_file": "examples/list_widget/main.go", "source_location": "L149"}], "edges": [{"source": "examples_list_widget_main_go", "target": "bytes", "relation": "imports_from", "confidence": "EXTRACTED", "source_file": "examples/list_widget/main.go", "source_location": "L20", "weight": 1.0}, {"source": "examples_list_widget_main_go", "target": "embed", "relation": "imports_from", "confidence": "EXTRACTED", "source_file": "examples/list_widget/main.go", "source_location": "L21", "weight": 1.0}, {"source": "examples_list_widget_main_go", "target": "image", "relation": "imports_from", "confidence": "EXTRACTED", "source_file": "examples/list_widget/main.go", "source_location": "L22", "weight": 1.0}, {"source": "examples_list_widget_main_go", "target": "color", "relation": "imports_from", "confidence": "EXTRACTED", "source_file": "examples/list_widget/main.go", "source_location": "L23", "weight": 1.0}, {"source": "examples_list_widget_main_go", "target": "log", "relation": "imports_from", "confidence": "EXTRACTED", "source_file": "examples/list_widget/main.go", "source_location": "L24", "weight": 1.0}, {"source": "examples_list_widget_main_go", "target": "image", "relation": "imports_from", "confidence": "EXTRACTED", "source_file": "examples/list_widget/main.go", "source_location": "L26", "weight": 1.0}, {"source": "examples_list_widget_main_go", "target": "constantutil", "relation": "imports_from", "confidence": "EXTRACTED", "source_file": "examples/list_widget/main.go", "source_location": "L27", "weight": 1.0}, {"source": "examples_list_widget_main_go", "target": "ebitenui", "relation": "imports_from", "confidence": "EXTRACTED", "source_file": "examples/list_widget/main.go", "source_location": "L29", "weight": 1.0}, {"source": "examples_list_widget_main_go", "target": "widget", "relation": "imports_from", "confidence": "EXTRACTED", "source_file": "examples/list_widget/main.go", "source_location": "L30", "weight": 1.0}, {"source": "examples_list_widget_main_go", "target": "v2", "relation": "imports_from", "confidence": "EXTRACTED", "source_file": "examples/list_widget/main.go", "source_location": "L31", "weight": 1.0}, {"source": "examples_list_widget_main_go", "target": "v2", "relation": "imports_from", "confidence": "EXTRACTED", "source_file": "examples/list_widget/main.go", "source_location": "L32", "weight": 1.0}, {"source": "examples_list_widget_main_go", "target": "autoebiten", "relation": "imports_from", "confidence": "EXTRACTED", "source_file": "examples/list_widget/main.go", "source_location": "L33", "weight": 1.0}, {"source": "examples_list_widget_main_go", "target": "autoui", "relation": "imports_from", "confidence": "EXTRACTED", "source_file": "examples/list_widget/main.go", "source_location": "L34", "weight": 1.0}, {"source": "examples_list_widget_main_go", "target": "list_widget_game", "relation": "contains", "confidence": "EXTRACTED", "source_file": "examples/list_widget/main.go", "source_location": "L40", "weight": 1.0}, {"source": "examples_list_widget_main_go", "target": "main_main", "relation": "contains", "confidence": "EXTRACTED", "source_file": "examples/list_widget/main.go", "source_location": "L44", "weight": 1.0}, {"source": "list_widget_game", "target": "list_widget_game_update", "relation": "method", "confidence": "EXTRACTED", "source_file": "examples/list_widget/main.go", "source_location": "L117", "weight": 1.0}, {"source": "list_widget_game", "target": "list_widget_game_draw", "relation": "method", "confidence": "EXTRACTED", "source_file": "examples/list_widget/main.go", "source_location": "L125", "weight": 1.0}, {"source": "list_widget_game", "target": "list_widget_game_layout", "relation": "method", "confidence": "EXTRACTED", "source_file": "examples/list_widget/main.go", "source_location": "L132", "weight": 1.0}, {"source": "examples_list_widget_main_go", "target": "main_loadfont", "relation": "contains", "confidence": "EXTRACTED", "source_file": "examples/list_widget/main.go", "source_location": "L136", "weight": 1.0}, {"source": "examples_list_widget_main_go", "target": "main_createbuttonimage", "relation": "contains", "confidence": "EXTRACTED", "source_file": "examples/list_widget/main.go", "source_location": "L149", "weight": 1.0}, {"source": "main_main", "target": "main_loadfont", "relation": "calls", "confidence": "EXTRACTED", "source_file": "examples/list_widget/main.go", "source_location": "L46", "weight": 1.0}, {"source": "main_main", "target": "main_createbuttonimage", "relation": "calls", "confidence": "EXTRACTED", "source_file": "examples/list_widget/main.go", "source_location": "L56", "weight": 1.0}], "raw_calls": [{"caller_nid": "main_main", "callee": "Fatal", "source_file": "examples/list_widget/main.go", "source_location": "L48"}, {"caller_nid": "main_main", "callee": "NewContainer", "source_file": "examples/list_widget/main.go", "source_location": "L52"}, {"caller_nid": "main_main", "callee": "GetWidget", "source_file": "examples/list_widget/main.go", "source_location": "L53"}, {"caller_nid": "main_main", "callee": "Rect", "source_file": "examples/list_widget/main.go", "source_location": "L53"}, {"caller_nid": "main_main", "callee": "NewList", "source_file": "examples/list_widget/main.go", "source_location": "L60"}, {"caller_nid": "main_main", "callee": "Entries", "source_file": "examples/list_widget/main.go", "source_location": "L61"}, {"caller_nid": "main_main", "callee": "EntryLabelFunc", "source_file": "examples/list_widget/main.go", "source_location": "L62"}, {"caller_nid": "main_main", "callee": "EntryFontFace", "source_file": "examples/list_widget/main.go", "source_location": "L65"}, {"caller_nid": "main_main", "callee": "ScrollContainerImage", "source_file": "examples/list_widget/main.go", "source_location": "L66"}, {"caller_nid": "main_main", "callee": "NewNineSliceColor", "source_file": "examples/list_widget/main.go", "source_location": "L67"}, {"caller_nid": "main_main", "callee": "NewNineSliceColor", "source_file": "examples/list_widget/main.go", "source_location": "L68"}, {"caller_nid": "main_main", "callee": "NewNineSliceColor", "source_file": "examples/list_widget/main.go", "source_location": "L69"}, {"caller_nid": "main_main", "callee": "SliderParams", "source_file": "examples/list_widget/main.go", "source_location": "L71"}, {"caller_nid": "main_main", "callee": "NewNineSliceColor", "source_file": "examples/list_widget/main.go", "source_location": "L73"}, {"caller_nid": "main_main", "callee": "NewNineSliceColor", "source_file": "examples/list_widget/main.go", "source_location": "L74"}, {"caller_nid": "main_main", "callee": "ConstantToPointer", "source_file": "examples/list_widget/main.go", "source_location": "L77"}, {"caller_nid": "main_main", "callee": "NewInsetsSimple", "source_file": "examples/list_widget/main.go", "source_location": "L78"}, {"caller_nid": "main_main", "callee": "HideHorizontalSlider", "source_file": "examples/list_widget/main.go", "source_location": "L80"}, {"caller_nid": "main_main", "callee": "EntryColor", "source_file": "examples/list_widget/main.go", "source_location": "L81"}, {"caller_nid": "main_main", "callee": "EntryTextPadding", "source_file": "examples/list_widget/main.go", "source_location": "L93"}, {"caller_nid": "main_main", "callee": "NewInsetsSimple", "source_file": "examples/list_widget/main.go", "source_location": "L93"}, {"caller_nid": "main_main", "callee": "GetWidget", "source_file": "examples/list_widget/main.go", "source_location": "L95"}, {"caller_nid": "main_main", "callee": "Rect", "source_file": "examples/list_widget/main.go", "source_location": "L95"}, {"caller_nid": "main_main", "callee": "GetWidget", "source_file": "examples/list_widget/main.go", "source_location": "L96"}, {"caller_nid": "main_main", "callee": "AddChild", "source_file": "examples/list_widget/main.go", "source_location": "L99"}, {"caller_nid": "main_main", "callee": "Register", "source_file": "examples/list_widget/main.go", "source_location": "L105"}, {"caller_nid": "main_main", "callee": "SetWindowSize", "source_file": "examples/list_widget/main.go", "source_location": "L109"}, {"caller_nid": "main_main", "callee": "SetWindowTitle", "source_file": "examples/list_widget/main.go", "source_location": "L110"}, {"caller_nid": "main_main", "callee": "RunGameWithOptions", "source_file": "examples/list_widget/main.go", "source_location": "L112"}, {"caller_nid": "main_main", "callee": "Fatal", "source_file": "examples/list_widget/main.go", "source_location": "L113"}, {"caller_nid": "list_widget_game_update", "callee": "Update", "source_file": "examples/list_widget/main.go", "source_location": "L118"}, {"caller_nid": "list_widget_game_update", "callee": "Update", "source_file": "examples/list_widget/main.go", "source_location": "L121"}, {"caller_nid": "list_widget_game_draw", "callee": "Fill", "source_file": "examples/list_widget/main.go", "source_location": "L126"}, {"caller_nid": "list_widget_game_draw", "callee": "Draw", "source_file": "examples/list_widget/main.go", "source_location": "L127"}, {"caller_nid": "list_widget_game_draw", "callee": "Capture", "source_file": "examples/list_widget/main.go", "source_location": "L128"}, {"caller_nid": "list_widget_game_draw", "callee": "DrawHighlights", "source_file": "examples/list_widget/main.go", "source_location": "L129"}, {"caller_nid": "main_loadfont", "callee": "NewGoTextFaceSource", "source_file": "examples/list_widget/main.go", "source_location": "L137"}, {"caller_nid": "main_loadfont", "callee": "NewReader", "source_file": "examples/list_widget/main.go", "source_location": "L137"}, {"caller_nid": "main_createbuttonimage", "callee": "NewNineSliceColor", "source_file": "examples/list_widget/main.go", "source_location": "L151"}, {"caller_nid": "main_createbuttonimage", "callee": "NewNineSliceColor", "source_file": "examples/list_widget/main.go", "source_location": "L152"}, {"caller_nid": "main_createbuttonimage", "callee": "NewNineSliceColor", "source_file": "examples/list_widget/main.go", "source_location": "L153"}, {"caller_nid": "main_createbuttonimage", "callee": "NewNineSliceColor", "source_file": "examples/list_widget/main.go", "source_location": "L154"}]}